nosuplodapi-0.0.2.dist-info/METADATA
nosuplodapi-0.0.2.dist-info/RECORD
nosuplodapi-0.0.2.dist-info/WHEEL
nosuplodapi-0.0.2.dist-info/top_level.txt
uploadapi/__init__.py
uploadapi/test.py
uploadapi/upload.py
