Metadata-Version: 2.1
Name: nosuplodapi
Version: 0.0.2
Summary: upload file to nos
Home-page: https://github.com/littlegrow
Author: littlegrow
Author-email: kfliuleigang@sina.com
License: UNKNOWN
Project-URL: Blog, https://littlegrow.top
Keywords: nos
Platform: UNKNOWN
Classifier: Programming Language :: Python :: 2.7
